pyscrew/__init__.py
pyscrew/main.py
pyscrew/config/__init__.py
pyscrew/config/pipeline.py
pyscrew/config/scenario.py
pyscrew/core/__init__.py
pyscrew/core/dataset.py
pyscrew/core/fields.py
pyscrew/core/run.py
pyscrew/core/step.py
pyscrew/pipeline/__init__.py
pyscrew/pipeline/loading.py
pyscrew/pipeline/processing.py
pyscrew/pipeline/validating.py
pyscrew/pipeline/transformers/__init__.py
pyscrew/pipeline/transformers/convert_dataset.py
pyscrew/pipeline/transformers/handle_duplicates.py
pyscrew/pipeline/transformers/handle_lengths.py
pyscrew/pipeline/transformers/handle_missings.py
pyscrew/pipeline/transformers/pipeline_logging.py
pyscrew/pipeline/transformers/unpack_steps.py
pyscrew/scenarios/s01.yml
pyscrew/scenarios/s02.yml
pyscrew/scenarios/s03.yml
pyscrew/scenarios/s04.yml
pyscrew/scenarios/s05.yml
pyscrew/scenarios/s06.yml
pyscrew/tools/calculate_scenario_metrics.py
pyscrew/tools/compress_json_data.py
pyscrew/tools/export_scenario_archive.py
pyscrew/tools/generate_csv_labels.py
pyscrew/utils/__init__.py
pyscrew/utils/logger.py
pyscrew/utils/resolver.py
pyscrew-1.2.1.dist-info/licenses/LICENSE
pyscrew-1.2.1.dist-info/METADATA
pyscrew-1.2.1.dist-info/WHEEL
pyscrew-1.2.1.dist-info/top_level.txt
pyscrew-1.2.1.dist-info/RECORD
