Metadata-Version: 2.4
Name: pyscrew
Version: 1.2.1
Summary: A Python package for accessing industrial research data from a screw driving system
Author-email: Nikolai West <nikolai.west@tu-dortmund.de>
License-Expression: CC-BY-4.0
Project-URL: Homepage, https://github.com/nikolaiwest/pyscrew
Project-URL: Bug Tracker, https://github.com/nikolaiwest/pyscrew/issues
Project-URL: Documentation, https://github.com/nikolaiwest/pyscrew#readme
Project-URL: Changelog, https://github.com/nikolaiwest/pyscrew/blob/main/CHANGELOG.md
Keywords: manufacturing,screw driving,industrial data,open data,research data
Classifier: Development Status :: 3 - Alpha
Classifier: Intended Audience :: Science/Research
Classifier: Programming Language :: Python :: 3
Classifier: Programming Language :: Python :: 3.11
Classifier: Topic :: Scientific/Engineering
Classifier: Operating System :: OS Independent
Classifier: Natural Language :: English
Classifier: Typing :: Typed
Requires-Python: >=3.11
License-File: LICENSE
Requires-Dist: requests<3.0.0,>=2.28.0
Requires-Dist: tqdm<5.0.0,>=4.65.0
Requires-Dist: pyyaml<7.0.0,>=6.0.0
Requires-Dist: pydantic<3.0.0,>=2.10.6
Requires-Dist: scikit-learn<2.0.0,>=1.6.1
Requires-Dist: pandas<3.0.0,>=2.2.3
Requires-Dist: typing-extensions<5.0.0,>=4.0.0
Provides-Extra: test
Requires-Dist: pytest<8.0.0,>=7.0.0; extra == "test"
Requires-Dist: pytest-cov<5.0.0,>=4.0.0; extra == "test"
Requires-Dist: black<24.0.0,>=23.0.0; extra == "test"
Requires-Dist: mypy<2.0.0,>=1.0.0; extra == "test"
Requires-Dist: ruff<1.0.0,>=0.0.280; extra == "test"
Dynamic: license-file
